pybix/__init__.py
pybix/__main__.py
pybix/api.py
pybix/graph.py
pybix/logging.ini
pybix-0.0.8.dist-info/LICENSE
pybix-0.0.8.dist-info/METADATA
pybix-0.0.8.dist-info/WHEEL
pybix-0.0.8.dist-info/top_level.txt
pybix-0.0.8.dist-info/RECORD
