Metadata-Version: 2.1
Name: pybix
Version: 0.0.8
Summary: Python based Zabbix API utility with helper functions 
Home-page: https://github.com/mattykay/pybix
Author: Matthew Kalnins
Author-email: pybix@matthewkalnins.com
License: UNKNOWN
Keywords: zabbix,monitoring,api
Platform: UNKNOWN
Classifier: Programming Language :: Python
Classifier: Programming Language :: Python :: 3
Classifier: Programming Language :: Python :: 3.6
Classifier: Programming Language :: Python :: 3.7
Classifier: License :: OSI Approved :: MIT License
Classifier: Operating System :: OS Independent
Classifier: Natural Language :: English
Classifier: Topic :: System :: Monitoring
Requires-Python: >=3.6
Requires-Dist: requests (>=2.22.0)
Requires-Dist: docopt (>=0.6.2)
